elasticdb/__init__.py
elasticdb/create.py
elasticdb/delete.py
elasticdb/retrieve.py
elasticdb/update.py
elasticdb-0.0.2.dist-info/LICENSE
elasticdb-0.0.2.dist-info/METADATA
elasticdb-0.0.2.dist-info/WHEEL
elasticdb-0.0.2.dist-info/top_level.txt
elasticdb-0.0.2.dist-info/RECORD
